{"meta":{"source":"GDELT Project","sourceUrl":"https://www.gdeltproject.org/","note":"Titulares indexados por GDELT (fuentes en inglés). Cada nota enlaza a su fuente original; encabezados sin resumir.","query":"Mexico (economy OR peso OR Banxico OR Sheinbaum OR nearshoring OR USMCA OR tariff OR inflation OR remittances) sourcelang:english","cadence":"continuous","fetchedAt":"2026-07-13T09:47:44.224Z","count":4},"articles":[{"title":"Mexico Markets : IPC & the Peso July 13 , 2026","url":"https://www.riotimesonline.com/mexico-markets-ipc-peso-monday-july-13-2026/","domain":"riotimesonline.com","date":"2026-07-13T07:00:00Z","tag":"markets"},{"title":"MEXICO :  Our Call for Justice for Our Missing Loved Ones Must Reach the World Just as World Cup Goals Do","url":"https://www.ipsnews.net/2026/07/mexico-our-call-for-justice-for-our-missing-loved-ones-must-reach-the-world-just-as-world-cup-goals-do/","domain":"ipsnews.net","date":"2026-07-13T05:45:00Z","tag":"economy"},{"title":"Mexico in the Top 10 Worldwide for Foreign Direct Investment","url":"https://gringogazette.com/mexico-in-the-top-10-worldwide-for-foreign-direct-investment/","domain":"gringogazette.com","date":"2026-07-13T05:15:00Z","tag":"trade"},{"title":"Trump trade agenda puts USMCA renewal at a critical crossroads","url":"https://weeklyblitz.net/2026/07/13/trumps-trade-agenda-puts-usmca-renewal-at-a-critical-crossroads/","domain":"weeklyblitz.net","date":"2026-07-12T19:15:00Z","tag":"trade"}]}